CeleryConfig/CeleryManager.py
CeleryConfig/__init__.py
CeleryConfig/apps.py
CeleryConfig/models.py
CeleryConfig/tests.py
CeleryConfig/migrations/0001_initial.py
CeleryConfig/migrations/__init__.py
FileLogs/FileLogManager.py
FileLogs/__init__.py
FileLogs/apps.py
FileLogs/models.py
FileLogs/tests.py
FileLogs/migrations/__init__.py
Request/TaskManager.py
Request/__init__.py
Request/admin.py
Request/apps.py
Request/models.py
Request/tests.py
Request/migrations/0001_initial.py
Request/migrations/0002_auto_20170320_1433.py
Request/migrations/0003_auto_20170320_1434.py
Request/migrations/0004_remove_taskdetail_parent_task_id.py
Request/migrations/__init__.py
app_unit_tests/__init__.py
app_unit_tests/admin.py
app_unit_tests/apps.py
app_unit_tests/celery.py
app_unit_tests/models.py
app_unit_tests/tests.py
app_unit_tests/views.py
app_unit_tests/migrations/__init__.py
orch_request_library/__init__.py
orch_request_library/models.py
orch_request_library/settings.py
orch_request_library/urls.py
orch_request_library/wsgi.py
orch_request_library-1.0.dist-info/DESCRIPTION.rst
orch_request_library-1.0.dist-info/METADATA
orch_request_library-1.0.dist-info/RECORD
orch_request_library-1.0.dist-info/WHEEL
orch_request_library-1.0.dist-info/metadata.json
orch_request_library-1.0.dist-info/top_level.txt
