Metadata-Version: 2.0
Name: orch-request-library
Version: 1.0
Summary: Library for Task management
Home-page: UNKNOWN
Author: kbajracharya
Author-email: UNKNOWN
License: Macquarie Cloud Services
Platform: UNKNOWN
